blaze_client/NonExistentResourceException.py
blaze_client/__init__.py
blaze_client/blaze_client.py
miabis_model/__init__.py
miabis_model/biobank.py
miabis_model/collection.py
miabis_model/collection_organization.py
miabis_model/condition.py
miabis_model/gender.py
miabis_model/incorrect_json_format.py
miabis_model/juristic_person.py
miabis_model/network.py
miabis_model/network_organization.py
miabis_model/observation.py
miabis_model/sample.py
miabis_model/sample_donor.py
miabis_model/storage_temperature.py
miabis_model/util/__init__.py
miabis_model/util/config.py
miabis_model/util/constants.py
miabis_model/util/parsing_util.py
miabis_model/util/util.py
miabis_on_fhir-1.2.0.dist-info/METADATA
miabis_on_fhir-1.2.0.dist-info/WHEEL
miabis_on_fhir-1.2.0.dist-info/top_level.txt
miabis_on_fhir-1.2.0.dist-info/RECORD
