Metadata-Version: 2.4
Name: MIABIS_on_FHIR
Version: 1.2.0
Summary: Library containing classes for easier handling of data according to the MIABIS on FHIR profile, as well as client for communication with sample blaze server
Author-email: Simon Konar <simon.konar@gmail.com>
License: MIT
Keywords: MIABIS,FHIR,model,profile,data,handling
Classifier: License :: OSI Approved :: MIT License
Classifier: Programming Language :: Python :: 3
Requires-Python: >=3.11
Requires-Dist: simple-icd-10>=2.0.0
Requires-Dist: fhirclient>=4.2.1
Requires-Dist: requests>=2.32
Requires-Dist: python-dateutil>=2.9.0
Provides-Extra: test
Requires-Dist: pytest>=8.3.0; extra == "test"
